{"schemaVersion":{"minor":3,"patch":0,"major":0},"primaryContentSections":[{"declarations":[{"platforms":["macOS"],"tokens":[{"kind":"keyword","text":"func"},{"kind":"text","text":" "},{"kind":"identifier","text":"renderToCache"},{"kind":"text","text":"("},{"kind":"externalParam","text":"characterID"},{"kind":"text","text":": "},{"kind":"typeIdentifier","text":"String","preciseIdentifier":"s:SS"},{"kind":"text","text":", "},{"kind":"externalParam","text":"poseHash"},{"kind":"text","text":": "},{"kind":"typeIdentifier","text":"UInt64","preciseIdentifier":"s:s6UInt64V"},{"kind":"text","text":", "},{"kind":"externalParam","text":"resolution"},{"kind":"text","text":": "},{"preciseIdentifier":"c:@S@CGSize","kind":"typeIdentifier","text":"CGSize"},{"kind":"text","text":"? = nil, "},{"kind":"externalParam","text":"commandBuffer"},{"kind":"text","text":" "},{"kind":"internalParam","text":"externalCommandBuffer"},{"kind":"text","text":": (any "},{"preciseIdentifier":"c:objc(pl)MTLCommandBuffer","kind":"typeIdentifier","text":"MTLCommandBuffer"},{"kind":"text","text":")? = nil, "},{"kind":"externalParam","text":"waitUntilCompleted"},{"kind":"text","text":": "},{"text":"Bool","kind":"typeIdentifier","preciseIdentifier":"s:Sb"},{"text":" = false, ","kind":"text"},{"text":"completion","kind":"externalParam"},{"text":": ((","kind":"text"},{"text":"SpriteCacheSystem","kind":"typeIdentifier","preciseIdentifier":"s:11VRMMetalKit17SpriteCacheSystemC","identifier":"doc:\/\/VRMMetalKit\/documentation\/VRMMetalKit\/SpriteCacheSystem"},{"text":".","kind":"text"},{"text":"CachedPose","kind":"typeIdentifier","preciseIdentifier":"s:11VRMMetalKit17SpriteCacheSystemC10CachedPoseV","identifier":"doc:\/\/VRMMetalKit\/documentation\/VRMMetalKit\/SpriteCacheSystem\/CachedPose"},{"text":"?) -> ","kind":"text"},{"text":"Void","kind":"typeIdentifier","preciseIdentifier":"s:s4Voida"},{"text":")? = nil, ","kind":"text"},{"text":"renderBlock","kind":"externalParam"},{"text":": (any ","kind":"text"},{"text":"MTLRenderCommandEncoder","kind":"typeIdentifier","preciseIdentifier":"c:objc(pl)MTLRenderCommandEncoder"},{"text":", any ","kind":"text"},{"text":"MTLTexture","kind":"typeIdentifier","preciseIdentifier":"c:objc(pl)MTLTexture"},{"text":") -> ","kind":"text"},{"text":"Void","kind":"typeIdentifier","preciseIdentifier":"s:s4Voida"},{"text":") -> ","kind":"text"},{"text":"SpriteCacheSystem","kind":"typeIdentifier","preciseIdentifier":"s:11VRMMetalKit17SpriteCacheSystemC","identifier":"doc:\/\/VRMMetalKit\/documentation\/VRMMetalKit\/SpriteCacheSystem"},{"text":".","kind":"text"},{"text":"CachedPose","kind":"typeIdentifier","preciseIdentifier":"s:11VRMMetalKit17SpriteCacheSystemC10CachedPoseV","identifier":"doc:\/\/VRMMetalKit\/documentation\/VRMMetalKit\/SpriteCacheSystem\/CachedPose"},{"text":"?","kind":"text"}],"languages":["swift"]}],"kind":"declarations"},{"parameters":[{"content":[{"type":"paragraph","inlineContent":[{"text":"Character identifier for cache management","type":"text"}]}],"name":"characterID"},{"content":[{"type":"paragraph","inlineContent":[{"text":"Unique pose hash for cache key (use ","type":"text"},{"type":"codeVoice","code":"computePoseHash()"},{"text":")","type":"text"}]}],"name":"poseHash"},{"content":[{"type":"paragraph","inlineContent":[{"text":"Texture resolution (nil = use ","type":"text"},{"type":"codeVoice","code":"defaultResolution"},{"text":" of 512×512)","type":"text"}]}],"name":"resolution"},{"content":[{"inlineContent":[{"type":"text","text":"Optional command buffer to encode into. If "},{"type":"codeVoice","code":"nil"},{"type":"text","text":", system creates one."},{"type":"text","text":" "},{"type":"text","text":"When provided, you must call "},{"type":"codeVoice","code":"commit()"},{"type":"text","text":" yourself. The system will NOT commit it."}],"type":"paragraph"}],"name":"externalCommandBuffer"},{"content":[{"inlineContent":[{"type":"text","text":"If "},{"type":"codeVoice","code":"true"},{"type":"text","text":" and no "},{"type":"codeVoice","code":"externalCommandBuffer"},{"type":"text","text":" provided, blocks until GPU finishes."},{"type":"text","text":" "},{"type":"text","text":"Ignored if "},{"type":"codeVoice","code":"externalCommandBuffer"},{"type":"text","text":" is provided (blocking with external buffers is caller’s responsibility)."},{"type":"text","text":" "},{"type":"text","text":"Default is "},{"type":"codeVoice","code":"false"},{"type":"text","text":" (async)."}],"type":"paragraph"}],"name":"waitUntilCompleted"},{"content":[{"type":"paragraph","inlineContent":[{"type":"text","text":"Optional callback invoked on "},{"type":"codeVoice","code":"callbackQueue"},{"type":"text","text":" (default "},{"type":"codeVoice","code":".main"},{"type":"text","text":") when render completes."},{"type":"text","text":" "},{"type":"text","text":"Receives "},{"type":"codeVoice","code":"CachedPose?"},{"type":"text","text":" - "},{"type":"codeVoice","code":"nil"},{"type":"text","text":" if caching failed."}]}],"name":"completion"},{"content":[{"type":"paragraph","inlineContent":[{"type":"text","text":"Closure that performs the actual rendering. Receives encoder and target texture."},{"type":"text","text":" "},{"type":"text","text":"Must be "},{"type":"codeVoice","code":"@Sendable"},{"type":"text","text":" for thread safety."}]}],"name":"renderBlock"}],"kind":"parameters"},{"content":[{"type":"heading","level":2,"text":"Return Value","anchor":"return-value"},{"type":"paragraph","inlineContent":[{"type":"text","text":""}]},{"type":"unorderedList","items":[{"content":[{"inlineContent":[{"type":"strong","inlineContent":[{"type":"text","text":"Synchronous path"}]},{"type":"text","text":" ("},{"type":"codeVoice","code":"waitUntilCompleted: true"},{"type":"text","text":", no external buffer): Returns "},{"type":"codeVoice","code":"CachedPose?"},{"type":"text","text":" immediately."}],"type":"paragraph"}]},{"content":[{"type":"paragraph","inlineContent":[{"inlineContent":[{"type":"text","text":"Async path"}],"type":"strong"},{"text":" (default): Returns ","type":"text"},{"code":"nil","type":"codeVoice"},{"text":". Use ","type":"text"},{"code":"completion","type":"codeVoice"},{"text":" handler to receive result.","type":"text"}]}]},{"content":[{"type":"paragraph","inlineContent":[{"inlineContent":[{"text":"Already pending","type":"text"}],"type":"strong"},{"type":"text","text":": Returns "},{"type":"codeVoice","code":"nil"},{"type":"text","text":" if this "},{"type":"codeVoice","code":"poseHash"},{"type":"text","text":" is already being rendered."}]}]},{"content":[{"inlineContent":[{"inlineContent":[{"type":"text","text":"Failure"}],"type":"strong"},{"type":"text","text":": Returns "},{"type":"codeVoice","code":"nil"},{"type":"text","text":" if texture allocation or encoding fails."}],"type":"paragraph"}]}]}],"kind":"content"},{"content":[{"anchor":"discussion","text":"Discussion","type":"heading","level":2},{"type":"paragraph","inlineContent":[{"inlineContent":[{"text":"Breaking Change (PR #38)","type":"text"}],"type":"strong"},{"text":": This method now supports async GPU rendering and returns ","type":"text"},{"code":"nil","type":"codeVoice"},{"text":" ","type":"text"},{"text":"when using the async path. Use the ","type":"text"},{"code":"completion","type":"codeVoice"},{"text":" handler to receive the cached pose when ready.","type":"text"}]},{"type":"paragraph","inlineContent":[{"inlineContent":[{"type":"text","text":"Thread Safety"}],"type":"strong"},{"text":": This method is thread-safe and prevents duplicate renders for the same ","type":"text"},{"code":"poseHash","type":"codeVoice"},{"text":".","type":"text"},{"text":" ","type":"text"},{"text":"If a render is already pending for the given pose, returns ","type":"text"},{"code":"nil","type":"codeVoice"},{"text":" immediately.","type":"text"}]},{"anchor":"Usage-Patterns","text":"Usage Patterns","type":"heading","level":2},{"anchor":"Synchronous-Blocking","text":"Synchronous (Blocking)","type":"heading","level":3},{"syntax":"swift","code":["let pose = cache.renderToCache(","    characterID: \"avatar1\",","    poseHash: hash,","    waitUntilCompleted: true  \/\/ Blocks until GPU finishes",") { encoder, texture in","    \/\/ Render your character here","}","\/\/ pose is non-nil and ready to use"],"type":"codeListing"},{"anchor":"Asynchronous-Non-Blocking-Recommended","text":"Asynchronous (Non-Blocking, Recommended)","type":"heading","level":3},{"syntax":"swift","code":["cache.renderToCache(","    characterID: \"avatar1\",","    poseHash: hash,","    completion: { cachedPose in","        \/\/ Called on callbackQueue when GPU finishes","        if let pose = cachedPose {","            \/\/ Use cached pose here","        }","    }",") { encoder, texture in","    \/\/ Render your character here","}","\/\/ Returns nil immediately, continues on GPU"],"type":"codeListing"},{"anchor":"Shared-Command-Buffer-Batching","text":"Shared Command Buffer (Batching)","type":"heading","level":3},{"syntax":"swift","code":["let commandBuffer = queue.makeCommandBuffer()!","","\/\/ Batch multiple renders into same command buffer","cache.renderToCache(characterID: \"avatar1\", poseHash: hash1,","                    commandBuffer: commandBuffer) { ... }","cache.renderToCache(characterID: \"avatar2\", poseHash: hash2,","                    commandBuffer: commandBuffer) { ... }","","commandBuffer.commit()  \/\/ Submit all renders at once"],"type":"codeListing"}],"kind":"content"}],"metadata":{"symbolKind":"method","modules":[{"name":"VRMMetalKit"}],"role":"symbol","externalID":"s:11VRMMetalKit17SpriteCacheSystemC08renderToD011characterID8poseHash10resolution13commandBuffer18waitUntilCompleted10completion0F5BlockAC10CachedPoseVSgSS_s6UInt64VSo6CGSizeVSgSo010MTLCommandN0_pSgSbyANYbcSgySo23MTLRenderCommandEncoder_p_So10MTLTexture_ptYbXEtF","fragments":[{"text":"func","kind":"keyword"},{"text":" ","kind":"text"},{"text":"renderToCache","kind":"identifier"},{"text":"(","kind":"text"},{"text":"characterID","kind":"externalParam"},{"text":": ","kind":"text"},{"text":"String","kind":"typeIdentifier","preciseIdentifier":"s:SS"},{"text":", ","kind":"text"},{"text":"poseHash","kind":"externalParam"},{"text":": ","kind":"text"},{"text":"UInt64","kind":"typeIdentifier","preciseIdentifier":"s:s6UInt64V"},{"text":", ","kind":"text"},{"text":"resolution","kind":"externalParam"},{"text":": ","kind":"text"},{"text":"CGSize","kind":"typeIdentifier","preciseIdentifier":"c:@S@CGSize"},{"text":"?, ","kind":"text"},{"text":"commandBuffer","kind":"externalParam"},{"text":": (any ","kind":"text"},{"text":"MTLCommandBuffer","kind":"typeIdentifier","preciseIdentifier":"c:objc(pl)MTLCommandBuffer"},{"text":")?, ","kind":"text"},{"text":"waitUntilCompleted","kind":"externalParam"},{"text":": ","kind":"text"},{"text":"Bool","kind":"typeIdentifier","preciseIdentifier":"s:Sb"},{"text":", ","kind":"text"},{"text":"completion","kind":"externalParam"},{"text":": ((","kind":"text"},{"text":"SpriteCacheSystem","kind":"typeIdentifier","preciseIdentifier":"s:11VRMMetalKit17SpriteCacheSystemC"},{"text":".","kind":"text"},{"text":"CachedPose","kind":"typeIdentifier","preciseIdentifier":"s:11VRMMetalKit17SpriteCacheSystemC10CachedPoseV"},{"text":"?) -> ","kind":"text"},{"text":"Void","kind":"typeIdentifier","preciseIdentifier":"s:s4Voida"},{"text":")?, ","kind":"text"},{"text":"renderBlock","kind":"externalParam"},{"text":": (any ","kind":"text"},{"text":"MTLRenderCommandEncoder","kind":"typeIdentifier","preciseIdentifier":"c:objc(pl)MTLRenderCommandEncoder"},{"text":", any ","kind":"text"},{"text":"MTLTexture","kind":"typeIdentifier","preciseIdentifier":"c:objc(pl)MTLTexture"},{"text":") -> ","kind":"text"},{"text":"Void","kind":"typeIdentifier","preciseIdentifier":"s:s4Voida"},{"text":") -> ","kind":"text"},{"text":"SpriteCacheSystem","kind":"typeIdentifier","preciseIdentifier":"s:11VRMMetalKit17SpriteCacheSystemC"},{"text":".","kind":"text"},{"text":"CachedPose","kind":"typeIdentifier","preciseIdentifier":"s:11VRMMetalKit17SpriteCacheSystemC10CachedPoseV"},{"text":"?","kind":"text"}],"roleHeading":"Instance Method","title":"renderToCache(characterID:poseHash:resolution:commandBuffer:waitUntilCompleted:completion:renderBlock:)"},"hierarchy":{"paths":[["doc:\/\/VRMMetalKit\/documentation\/VRMMetalKit","doc:\/\/VRMMetalKit\/documentation\/VRMMetalKit\/SpriteCacheSystem"]]},"variants":[{"traits":[{"interfaceLanguage":"swift"}],"paths":["\/documentation\/vrmmetalkit\/spritecachesystem\/rendertocache(characterid:posehash:resolution:commandbuffer:waituntilcompleted:completion:renderblock:)"]}],"kind":"symbol","abstract":[{"type":"text","text":"Render a character pose directly to a cached texture"}],"identifier":{"interfaceLanguage":"swift","url":"doc:\/\/VRMMetalKit\/documentation\/VRMMetalKit\/SpriteCacheSystem\/renderToCache(characterID:poseHash:resolution:commandBuffer:waitUntilCompleted:completion:renderBlock:)"},"sections":[],"references":{"doc://VRMMetalKit/documentation/VRMMetalKit/SpriteCacheSystem/renderToCache(characterID:poseHash:resolution:commandBuffer:waitUntilCompleted:completion:renderBlock:)":{"url":"\/documentation\/vrmmetalkit\/spritecachesystem\/rendertocache(characterid:posehash:resolution:commandbuffer:waituntilcompleted:completion:renderblock:)","identifier":"doc:\/\/VRMMetalKit\/documentation\/VRMMetalKit\/SpriteCacheSystem\/renderToCache(characterID:poseHash:resolution:commandBuffer:waitUntilCompleted:completion:renderBlock:)","type":"topic","role":"symbol","title":"renderToCache(characterID:poseHash:resolution:commandBuffer:waitUntilCompleted:completion:renderBlock:)","fragments":[{"kind":"keyword","text":"func"},{"kind":"text","text":" "},{"kind":"identifier","text":"renderToCache"},{"kind":"text","text":"("},{"kind":"externalParam","text":"characterID"},{"kind":"text","text":": "},{"kind":"typeIdentifier","preciseIdentifier":"s:SS","text":"String"},{"kind":"text","text":", "},{"kind":"externalParam","text":"poseHash"},{"kind":"text","text":": "},{"kind":"typeIdentifier","preciseIdentifier":"s:s6UInt64V","text":"UInt64"},{"kind":"text","text":", "},{"kind":"externalParam","text":"resolution"},{"kind":"text","text":": "},{"kind":"typeIdentifier","preciseIdentifier":"c:@S@CGSize","text":"CGSize"},{"kind":"text","text":"?, "},{"kind":"externalParam","text":"commandBuffer"},{"kind":"text","text":": (any "},{"kind":"typeIdentifier","preciseIdentifier":"c:objc(pl)MTLCommandBuffer","text":"MTLCommandBuffer"},{"kind":"text","text":")?, "},{"kind":"externalParam","text":"waitUntilCompleted"},{"kind":"text","text":": "},{"kind":"typeIdentifier","preciseIdentifier":"s:Sb","text":"Bool"},{"kind":"text","text":", "},{"kind":"externalParam","text":"completion"},{"kind":"text","text":": (("},{"kind":"typeIdentifier","preciseIdentifier":"s:11VRMMetalKit17SpriteCacheSystemC","text":"SpriteCacheSystem"},{"kind":"text","text":"."},{"kind":"typeIdentifier","preciseIdentifier":"s:11VRMMetalKit17SpriteCacheSystemC10CachedPoseV","text":"CachedPose"},{"kind":"text","text":"?) -> "},{"kind":"typeIdentifier","preciseIdentifier":"s:s4Voida","text":"Void"},{"kind":"text","text":")?, "},{"kind":"externalParam","text":"renderBlock"},{"kind":"text","text":": (any "},{"kind":"typeIdentifier","preciseIdentifier":"c:objc(pl)MTLRenderCommandEncoder","text":"MTLRenderCommandEncoder"},{"kind":"text","text":", any "},{"kind":"typeIdentifier","preciseIdentifier":"c:objc(pl)MTLTexture","text":"MTLTexture"},{"kind":"text","text":") -> "},{"kind":"typeIdentifier","preciseIdentifier":"s:s4Voida","text":"Void"},{"kind":"text","text":") -> "},{"kind":"typeIdentifier","preciseIdentifier":"s:11VRMMetalKit17SpriteCacheSystemC","text":"SpriteCacheSystem"},{"kind":"text","text":"."},{"kind":"typeIdentifier","preciseIdentifier":"s:11VRMMetalKit17SpriteCacheSystemC10CachedPoseV","text":"CachedPose"},{"kind":"text","text":"?"}],"kind":"symbol","abstract":[{"type":"text","text":"Render a character pose directly to a cached texture"}]},"doc://VRMMetalKit/documentation/VRMMetalKit/SpriteCacheSystem/CachedPose":{"fragments":[{"text":"struct","kind":"keyword"},{"text":" ","kind":"text"},{"text":"CachedPose","kind":"identifier"}],"title":"SpriteCacheSystem.CachedPose","abstract":[{"type":"text","text":"A cached sprite representing a specific character pose."}],"kind":"symbol","identifier":"doc:\/\/VRMMetalKit\/documentation\/VRMMetalKit\/SpriteCacheSystem\/CachedPose","type":"topic","role":"symbol","navigatorTitle":[{"text":"CachedPose","kind":"identifier"}],"url":"\/documentation\/vrmmetalkit\/spritecachesystem\/cachedpose"},"doc://VRMMetalKit/documentation/VRMMetalKit":{"type":"topic","identifier":"doc:\/\/VRMMetalKit\/documentation\/VRMMetalKit","url":"\/documentation\/vrmmetalkit","kind":"symbol","title":"VRMMetalKit","role":"collection","abstract":[{"text":"High-performance loading, rendering, and animation of VRM 1.0 avatars on Apple platforms, built on Metal.","type":"text"}]},"doc://VRMMetalKit/documentation/VRMMetalKit/SpriteCacheSystem":{"title":"SpriteCacheSystem","navigatorTitle":[{"text":"SpriteCacheSystem","kind":"identifier"}],"abstract":[{"type":"text","text":"Texture cache of pre-rendered avatar poses; targets 60 FPS with 5+ characters by reusing sprites for static or near-static poses."}],"role":"symbol","kind":"symbol","type":"topic","identifier":"doc:\/\/VRMMetalKit\/documentation\/VRMMetalKit\/SpriteCacheSystem","url":"\/documentation\/vrmmetalkit\/spritecachesystem","fragments":[{"text":"class","kind":"keyword"},{"text":" ","kind":"text"},{"text":"SpriteCacheSystem","kind":"identifier"}]}}}